indico_payment_opencollective/__init__.py
indico_payment_opencollective/blueprint.py
indico_payment_opencollective/constants.py
indico_payment_opencollective/controllers.py
indico_payment_opencollective/plugin.py
indico_payment_opencollective/static/images/logo.png
indico_payment_opencollective/templates/event_payment_form.html
indico_payment_opencollective/templates/transaction_details.html
indico_plugin_payment_opencollective-0.1.1.dist-info/METADATA
indico_plugin_payment_opencollective-0.1.1.dist-info/WHEEL
indico_plugin_payment_opencollective-0.1.1.dist-info/entry_points.txt
indico_plugin_payment_opencollective-0.1.1.dist-info/licenses/LICENSE
indico_plugin_payment_opencollective-0.1.1.dist-info/RECORD
