Metadata-Version: 2.3
Name: indico-plugin-payment-opencollective
Version: 0.1.1
Summary: Indico payment plugin for processing payment with Open Collective
Project-URL: GitHub, https://github.com/sukso96100/indico-plugin-payment-opencollective
Author-email: Youngbin Han <ybhan@ubuntu.com>
License: MIT License
License-File: LICENSE
Classifier: Environment :: Plugins
Classifier: Environment :: Web Environment
Classifier: License :: OSI Approved :: MIT License
Classifier: Programming Language :: Python :: 3.12
Requires-Python: >=3.12
Requires-Dist: gql[requests]>=3.5.0
Requires-Dist: indico>=3.3
